dappier_mcp/__init__.py
dappier_mcp/server.py
mseep_dappier_mcp-0.3.6.dist-info/licenses/LICENSE
mseep_dappier_mcp-0.3.6.dist-info/METADATA
mseep_dappier_mcp-0.3.6.dist-info/WHEEL
mseep_dappier_mcp-0.3.6.dist-info/entry_points.txt
mseep_dappier_mcp-0.3.6.dist-info/top_level.txt
mseep_dappier_mcp-0.3.6.dist-info/RECORD
